CMakeLists.txt
LICENSE.md
MANIFEST.in
README.rst
pyproject.toml
setup.cfg
setup.py
versioneer.py
cmake/FindGLPK.cmake
cmake/FindSUNDIALS.cmake
cmake/README.md
src/dfba/__init__.py
src/dfba/_version.py
src/dfba/control.py
src/dfba/exchange.py
src/dfba/helpers.py
src/dfba/jit.py
src/dfba/library.py
src/dfba/model.py
src/dfba/types.py
src/dfba/variable.py
src/dfba.egg-info/PKG-INFO
src/dfba.egg-info/SOURCES.txt
src/dfba.egg-info/dependency_links.txt
src/dfba.egg-info/not-zip-safe
src/dfba.egg-info/requires.txt
src/dfba.egg-info/top_level.txt
src/dfba/plot/__init__.py
src/dfba/plot/matplotlib.py
src/dfba/plot/plotly.py
src/extension/dfba_utils.cpp
src/extension/solver_data.h
src/extension/user_data.h
src/extension/emblp/README.md
src/extension/emblp/emblp.cpp
src/extension/emblp/emblp.h
src/extension/emblp/emblp_direct.cpp
src/extension/emblp/emblp_harwood.cpp
src/extension/emblp/emblp_scott.cpp
src/extension/methods/README.md
src/extension/methods/methods.cpp
src/extension/methods/methods.h
src/extension/methods/methods_direct.cpp
src/extension/methods/methods_harwood.cpp
src/extension/methods/methods_scott.cpp