Metadata-Version: 2.1
Name: dfba
Version: 0.1.8
Summary: Object-oriented software for dynamic flux-balance simulations.
Home-page: https://gitlab.com/davidtourigny/dynamic-fba
Author: David S. Tourigny, Moritz E. Beber
Author-email: dst2156@cumc.columbia.edu, morbeb@biosustain.dtu.dk
License: GNU GPL v3+
Download-URL: https://pypi.org/project/dfba/
Keywords: dynamic,flux-balance analysis,FBA,DFBA,DAE
Platform: UNKNOWN
Classifier: Development Status :: 3 - Alpha
Classifier: Intended Audience :: Science/Research
Classifier: License :: OSI Approved :: GNU General Public License v3 or later (GPLv3+)
Classifier: Natural Language :: English
Classifier: Operating System :: MacOS :: MacOS X
Classifier: Operating System :: POSIX
Classifier: Programming Language :: Python :: 3.6
Classifier: Programming Language :: Python :: 3.7
Classifier: Programming Language :: Python :: 3 :: Only
Classifier: Topic :: Scientific/Engineering :: Bio-Informatics
Requires-Python: >=3.6
Provides-Extra: development
Provides-Extra: matplotlib
Provides-Extra: plotly
